XitongShejiRumen/README.md
XitongShejiRumen/__init__.py
XitongShejiRumen/__main__.py
XitongShejiRumen/file.epub
XitongShejiRumen/index.html
XitongShejiRumen/css/__init__.py
XitongShejiRumen/css/annotations.css
XitongShejiRumen/css/main.css
XitongShejiRumen/css/normalize.css
XitongShejiRumen/css/popup.css
XitongShejiRumen/font/__init__.py
XitongShejiRumen/font/fontello.eot
XitongShejiRumen/font/fontello.svg
XitongShejiRumen/font/fontello.ttf
XitongShejiRumen/font/fontello.woff
XitongShejiRumen/img/__init__.py
XitongShejiRumen/img/annotator-glyph-sprite.png
XitongShejiRumen/img/annotator-icon-sprite.png
XitongShejiRumen/img/apple-touch-icon.png
XitongShejiRumen/img/cancelfullscreen.png
XitongShejiRumen/img/close.png
XitongShejiRumen/img/fullscreen.png
XitongShejiRumen/img/loader.gif
XitongShejiRumen/img/menu-icon.png
XitongShejiRumen/img/save.png
XitongShejiRumen/img/saved.png
XitongShejiRumen/img/settings-s.png
XitongShejiRumen/img/settings.png
XitongShejiRumen/img/star.png
XitongShejiRumen/js/__init__.py
XitongShejiRumen/js/epub.js
XitongShejiRumen/js/epub.min.js
XitongShejiRumen/js/epub.min.map
XitongShejiRumen/js/hooks.min.js
XitongShejiRumen/js/hooks.min.map
XitongShejiRumen/js/reader.js
XitongShejiRumen/js/reader.js.map
XitongShejiRumen/js/reader.min.js
XitongShejiRumen/js/reader.min.map
XitongShejiRumen/js/hooks/__init__.py
XitongShejiRumen/js/hooks/extensions/__init__.py
XitongShejiRumen/js/hooks/extensions/highlight.js
XitongShejiRumen/js/libs/__init__.py
XitongShejiRumen/js/libs/jquery.min.js
XitongShejiRumen/js/libs/localforage.min.js
XitongShejiRumen/js/libs/screenfull.js
XitongShejiRumen/js/libs/screenfull.min.js
XitongShejiRumen/js/libs/zip.min.js
XitongShejiRumen/js/plugins/__init__.py
XitongShejiRumen/js/plugins/hypothesis.js
XitongShejiRumen/js/plugins/search.js
xitong_sheji_rumen-2024.3.2.0.dist-info/METADATA
xitong_sheji_rumen-2024.3.2.0.dist-info/WHEEL
xitong_sheji_rumen-2024.3.2.0.dist-info/entry_points.txt
xitong_sheji_rumen-2024.3.2.0.dist-info/top_level.txt
xitong_sheji_rumen-2024.3.2.0.dist-info/RECORD
